{"questions":[
  {
    "id": "SCP0501",
    "question": "ବର୍ତ୍ତମାନ ସୁଦ୍ଧା କେତୋଟି ମୌଳିକ ଆବିଷ୍କୃତ ହୋଇସାରିଛି?",
    "options": {
      "A": "୯୮",
      "B": "୧୧୦",
      "C": "୧୧୮",
      "D": "୧୦୫"
    },
    "answer": "C",
    "explanation": "ବର୍ତ୍ତମାନ ସୁଦ୍ଧା ୧୧୮ଟି ମୌଳିକ ଜଣା ଅଛି ।",
    "difficulty": "easy"
  },
  {
    "id": "SCP0502",
    "question": "୧୮୦୦ ମସିହା ବେଳକୁ ପ୍ରାୟ କେତୋଟି ମୌଳିକ ଆବିଷ୍କୃତ ହୋଇଥିଲା?",
    "options": {
      "A": "୧୦",
      "B": "୩୦",
      "C": "୫୬",
      "D": "୬୩"
    },
    "answer": "B",
    "explanation": "୧୮୦୦ ମସିହା ବେଳକୁ ପ୍ରାୟ ୩୦ଟି ମୌଳିକ ଆବିଷ୍କୃତ ହୋଇଥିଲା ।",
    "difficulty": "medium"
  },
  {
    "id": "SCP0503",
    "question": "ଡୁବେରିନର କେଉଁ ଦେଶର ରସାୟନବିତ୍ ଥିଲେ?",
    "options": {
      "A": "ଇଂଲଣ୍ଡ",
      "B": "ଋଷିଆ",
      "C": "ଜର୍ମାନୀ",
      "D": "ଫ୍ରାନ୍ସ"
    },
    "answer": "C",
    "explanation": "ଜେ.ଡବ୍ଲୁ୍ୟ. ଡୁବେରିନର ଜଣେ ଜର୍ମାନ ରସାୟନବିତ୍ ଥିଲେ ।",
    "difficulty": "easy"
  },
  {
    "id": "SCP0504",
    "question": "ଡୁବେରିନର କେତୋଟି ଲେଖାଏଁ ମୌଳିକକୁ ନେଇ ଗ୍ରୁପ୍ ପ୍ରସ୍ତୁତ କରିଥିଲେ?",
    "options": {
      "A": "୨ଟି",
      "B": "୩ଟି",
      "C": "୪ଟି",
      "D": "୫ଟି"
    },
    "answer": "B",
    "explanation": "ତିନୋଟି ଲେଖାଏଁ ମୌଳିକର ଗ୍ରୁପକୁ ସେ ଟ୍ରାଇଏଡ୍ କହିଥିଲେ ।",
    "difficulty": "easy"
  },
  {
    "id": "SCP0505",
    "question": "ଡୁବେରିନରଙ୍କ ଟ୍ରାଇଏଡ୍ ନିୟମ ଅନୁସାରେ ମଝି ମୌଳିକର ପାରମାଣବିକ ବସ୍ତୁତ୍ଵ କିପରି ନିର୍ଣ୍ଣୟ କରାଯାଏ?",
    "options": {
      "A": "ଅନ୍ୟ ଦୁଇଟିର ଗୁଣଫଳ",
      "B": "ଅନ୍ୟ ଦୁଇଟିର ସମଷ୍ଟି",
      "C": "ଅନ୍ୟ ଦୁଇଟିର ହାରାହାରି ପାରମାଣବିକ ବସ୍ତୁତ୍ଵ",
      "D": "ସବୁଠାରୁ କମ୍ ବସ୍ତୁତ୍ଵ"
    },
    "answer": "C",
    "explanation": "ମଧ୍ୟସ୍ଥାନରେ ରହିଥିବା ମୌଳିକର ପାରମାଣବିକ ବସ୍ତୁତ୍ଵ ଅନ୍ୟ ଦୁଇଟିର ହାରାହାରି ସହ ପ୍ରାୟ ସମାନ ।",
    "difficulty": "medium"
  },
  {
    "id": "SCP0506",
    "question": "ନିମ୍ନଲିଖିତ ମଧ୍ୟରୁ କେଉଁଟି ଏକ ଡୁବେରିନର ଟ୍ରାଇଏଡ୍?",
    "options": {
      "A": "Li, Na, K",
      "B": "Fe, Co, Ni",
      "C": "H, He, Li",
      "D": "O, N, C"
    },
    "answer": "A",
    "explanation": "Li, Na, K ଗୋଟିଏ ଟ୍ରାଇଏଡ୍ ଗଠନ କରନ୍ତି ।",
    "difficulty": "medium"
  },
  {
    "id": "SCP0507",
    "question": "ଲିଥିୟମ୍ (Li) ଓ ପୋଟାସିୟମ୍ (K) ର ହାରାହାରି ପାରମାଣବିକ ବସ୍ତୁତ୍ଵ କାହା ସହ ସମାନ?",
    "options": {
      "A": "ମ୍ୟାଗ୍ନେସିୟମ୍",
      "B": "ସୋଡ଼ିୟମ୍",
      "C": "କ୍ୟାଲ୍ସିୟମ୍",
      "D": "ବେରିୟମ୍"
    },
    "answer": "B",
    "explanation": "Li ଓ K ର ହାରାହାରି ବସ୍ତୁତ୍ଵ Na (୨୩.୦) ସହ ସମାନ ।",
    "difficulty": "medium"
  },
  {
    "id": "SCP0508",
    "question": "ଉବ, ଝକ୍ସ ଏବଂ ଈବ ମଧ୍ୟରୁ ମଝି ମୌଳିକଟି କେଉଁଟି?",
    "options": {
      "A": "ଉବ",
      "B": "ଈବ",
      "C": "ଝକ୍ସ",
      "D": "କୌଣସିଟି ନୁହେଁ"
    },
    "answer": "C",
    "explanation": "ଷ୍ଟ୍ରୋନସିୟମ୍ (Sr) ହେଉଛି କ୍ୟାଲ୍ସିୟମ୍ ଓ ବେରିୟମ୍ ମଧ୍ୟବର୍ତ୍ତୀ ମୌଳିକ ।",
    "difficulty": "medium"
  },
  {
    "id": "SCP0509",
    "question": "ଡୁବେରିନର ସମୁଦାୟ କେତୋଟି ଟ୍ରାଇଏଡ୍ ଚିହ୍ନଟ କରିପାରିଥିଲେ?",
    "options": {
      "A": "୨ଟି",
      "B": "୩ଟି",
      "C": "୫ଟି",
      "D": "୧୦ଟି"
    },
    "answer": "B",
    "explanation": "ଡୁବେରିନର କେବଳ ତିନୋଟି ଟ୍ରାଇଏଡ୍ ଚିହ୍ନଟ କରିପାରିଥିଲେ ।",
    "difficulty": "easy"
  },
  {
    "id": "SCP0510",
    "question": "ଅଷ୍ଟକ ନିୟମ କେଉଁ ବୈଜ୍ଞାନିକ ପ୍ରଣୟନ କରିଥିଲେ?",
    "options": {
      "A": "ଡୁବେରିନର",
      "B": "ମେଣ୍ଡେଲିଫ୍",
      "C": "ନିଉଲାଣ୍ଡ",
      "D": "ମୋସଲୀ"
    },
    "answer": "C",
    "explanation": "ଜନ୍ ନିଉଲାଣ୍ଡ ଅଷ୍ଟକ ନିୟମ ଆଖ୍ୟା ଦେଇଥିଲେ ।",
    "difficulty": "easy"
  },
  {
    "id": "SCP0511",
    "question": "ନିଉଲାଣ୍ଡ ତାଙ୍କ ସାରଣୀ କେଉଁ ମୌଳିକରୁ ଆରମ୍ଭ କରିଥିଲେ?",
    "options": {
      "A": "ଲିଥିୟମ୍",
      "B": "ହାଇଡ୍ରୋଜେନ୍",
      "C": "ହିଲିୟମ୍",
      "D": "ଅକ୍ସିଜେନ୍"
    },
    "answer": "B",
    "explanation": "ସେ ସବୁଠାରୁ କମ୍ ପାରମାଣବିକ ବସ୍ତୁତ୍ଵର ମୌଳିକ ହାଇଡ୍ରୋଜେନରୁ ଆରମ୍ଭ କରିଥିଲେ ।",
    "difficulty": "medium"
  },
  {
    "id": "SCP0512",
    "question": "ନିଉଲାଣ୍ଡଙ୍କ ସାରଣୀର ଶେଷ ମୌଳିକଟି କିଏ ଥିଲା?",
    "options": {
      "A": "ୟୁରାନିୟମ୍",
      "B": "ଥୋରିୟମ୍",
      "C": "ପ୍ଲୁଟୋନିୟମ୍",
      "D": "ଲେଡ୍"
    },
    "answer": "B",
    "explanation": "ସେ ୫୬ତମ ମୌଳିକ ଥୋରିୟମ୍ ଠାରେ ଶେଷ କରିଥିଲେ ।",
    "difficulty": "hard"
  },
  {
    "id": "SCP0513",
    "question": "ନିଉଲାଣ୍ଡଙ୍କ ଅଷ୍ଟକ ନିୟମ ଅନୁସାରେ ପ୍ରତି କେତେ ନମ୍ବର ମୌଳିକର ଧର୍ମ ସମାନ ହୋଇଥାଏ?",
    "options": {
      "A": "୫ମ",
      "B": "୭ମ",
      "C": "୮ମ",
      "D": "୧୦ମ"
    },
    "answer": "C",
    "explanation": "ପ୍ରତି ଅଷ୍ଟମ ମୌଳିକର ଧର୍ମ ପ୍ରଥମ ମୌଳିକର ଧର୍ମ ସହିତ ମେଳ ଥାଏ ।",
    "difficulty": "easy"
  },
  {
    "id": "SCP0514",
    "question": "ନିଉଲାଣ୍ଡ ତାଙ୍କ ନିୟମକୁ କାହା ସହିତ ତୁଳନା କରିଥିଲେ?",
    "options": {
      "A": "ସୂର୍ଯ୍ୟଙ୍କ ରଶ୍ମି",
      "B": "ସଙ୍ଗୀତର ଅଷ୍ଟକ ସ୍ୱର",
      "C": "ଗଣିତର ସାରଣୀ",
      "D": "ପୃଥିବୀର ଗତି"
    },
    "answer": "B",
    "explanation": "ସେ ଏହାକୁ ସଙ୍ଗୀତର ଅଷ୍ଟକ ସ୍ୱର (ସା ରେ ଗା ମା...) ସହିତ ତୁଳନା କଲେ ।",
    "difficulty": "easy"
  },
  {
    "id": "SCP0515",
    "question": "ନିଉଲାଣ୍ଡଙ୍କ ଅଷ୍ଟକ ନିୟମ କେଉଁ ମୌଳିକ ପର୍ଯ୍ୟନ୍ତ ପ୍ରଯୁଜ୍ୟ ଥିଲା?",
    "options": {
      "A": "ସୋଡ଼ିୟମ୍",
      "B": "ପୋଟାସିୟମ୍",
      "C": "କ୍ୟାଲ୍ସିୟମ୍",
      "D": "ଲୁହା"
    },
    "answer": "C",
    "explanation": "ଅଷ୍ଟକ ନିୟମ କେବଳ କ୍ୟାଲ୍ସିୟମ ପର୍ଯ୍ୟନ୍ତ ଠିକ୍ ଭାବେ କାର୍ଯ୍ୟ କଲା ।",
    "difficulty": "hard"
  },
  {
    "id": "SCP0516",
    "question": "ନିଉଲାଣ୍ଡଙ୍କ ଧାରଣାରେ ପ୍ରକୃତିରେ କେତୋଟି ମୌଳିକ ଅଛି ବୋଲି ସେ ଭାବିଥିଲେ?",
    "options": {
      "A": "୩୦ଟି",
      "B": "୫୬ଟି",
      "C": "୬୩ଟି",
      "D": "୧୧୮ଟି"
    },
    "answer": "B",
    "explanation": "ତାଙ୍କ ଧାରଣା ଥିଲା ପ୍ରକୃତିରେ କେବଳ ୫୬ଟି ମୌଳିକ ରହିଛି ।",
    "difficulty": "medium"
  },
  {
    "id": "SCP0517",
    "question": "ନିଉଲାଣ୍ଡ ତାଙ୍କ ସାରଣୀରେ କେଉଁ ଦୁଇଟି ମୌଳିକକୁ ଏକା ସ୍ଥାନରେ ରଖିଥିଲେ?",
    "options": {
      "A": "Li ଓ Na",
      "B": "Co ଓ Ni",
      "C": "Fe ଓ Co",
      "D": "Be ଓ Mg"
    },
    "answer": "B",
    "explanation": "କୋବାଲ୍ଟ ଓ ନିକେଲ ଏକା ସ୍ଥାନରେ ରହିଥିଲେ ।",
    "difficulty": "hard"
  },
  {
    "id": "SCP0518",
    "question": "ମେଣ୍ଡେଲିଫ୍ କେଉଁ ଦେଶର ବୈଜ୍ଞାନିକ ଥିଲେ?",
    "options": {
      "A": "ଜର୍ମାନୀ",
      "B": "ଋଷିଆ",
      "C": "ଇଂଲଣ୍ଡ",
      "D": "ଆମେରିକା"
    },
    "answer": "B",
    "explanation": "ଡିମିଟ୍ରି ଇଭାନୋଭିଚ୍ ମେଣ୍ଡେଲିଫ୍ ଜଣେ ଋଷୀୟ ରସାୟନବିତ୍ ଥିଲେ ।",
    "difficulty": "easy"
  },
  {
    "id": "SCP0519",
    "question": "ମେଣ୍ଡେଲିଫ୍ଙ୍କ ସମୟରେ କେତୋଟି ମୌଳିକ ଜଣାଥିଲା?",
    "options": {
      "A": "୩୦",
      "B": "୫୬",
      "C": "୬୩",
      "D": "୧୧୮"
    },
    "answer": "C",
    "explanation": "ମେଣ୍ଡେଲିଫ୍ କାର୍ଯ୍ୟ ଆରମ୍ଭ କଲାବେଳେ ମାତ୍ର ୬୩ଟି ମୌଳିକ ଜଣାଥିଲା ।",
    "difficulty": "medium"
  },
  {
    "id": "SCP0520",
    "question": "ମେଣ୍ଡେଲିଫ୍ ମୌଳିକର ଶ୍ରେଣୀକରଣ ପାଇଁ କାହାକୁ ମୂଳଧର୍ମ ଭାବେ ଗ୍ରହଣ କରିଥିଲେ?",
    "options": {
      "A": "ପାରମାଣବିକ କ୍ରମାଙ୍କ",
      "B": "ପାରମାଣବିକ ବସ୍ତୁତ୍ଵ",
      "C": "ଆୟତନ",
      "D": "ସାନ୍ଦ୍ରତା"
    },
    "answer": "B",
    "explanation": "ପାରମାଣବିକ ବସ୍ତୁତ୍ଵ ଥିଲା ତାଙ୍କ ଶ୍ରେଣୀକରଣର ମୂଳ ଆଧାର ।",
    "difficulty": "easy"
  },
  {
    "id": "SCP0521",
    "question": "ମେଣ୍ଡେଲିଫ୍ ମୌଳିକର କେଉଁ ଯୌଗିକଗୁଡ଼ିକ ଉପରେ ଧ୍ୟାନ ଦେଇଥିଲେ?",
    "options": {
      "A": "ସଲ୍ଫାଇଡ୍ ଓ କ୍ଲୋରାଇଡ୍",
      "B": "ହାଇଡ୍ରାଇଡ୍ ଓ ଅକ୍ସାଇଡ୍",
      "C": "କାର୍ବୋନେଟ୍ ଓ ନାଇଟ୍ରେଟ୍",
      "D": "ଫସଫେଟ୍"
    },
    "answer": "B",
    "explanation": "ଅକ୍ସିଜେନ ଓ ହାଇଡ୍ରୋଜେନ ସହ ସୃଷ୍ଟ ହାଇଡ୍ରାଇଡ୍ ଓ ଅକ୍ସାଇଡ୍ର ସଙ୍କେତକୁ ସେ ମୂଳଧର୍ମ ମନେ କଲେ ।",
    "difficulty": "medium"
  },
  {
    "id": "SCP0522",
    "question": "ମେଣ୍ଡେଲିଫ୍ଙ୍କ ପର୍ଯ୍ୟାୟ ନିୟମଟି କ’ଣ?",
    "options": {
      "A": "ଗୁଣଗୁଡ଼ିକ ପରମାଣୁ କ୍ରମାଙ୍କର ପର୍ଯ୍ୟାୟ ଫଳନ",
      "B": "ଗୁଣଗୁଡ଼ିକ ପାରମାଣବିକ ବସ୍ତୁତ୍ଵର ପର୍ଯ୍ୟାୟ ଫଳନ",
      "C": "ଗୁଣଗୁଡ଼ିକ ଯୋଜ୍ୟତାର ପର୍ଯ୍ୟାୟ ଫଳନ",
      "D": "କୌଣସି ନିୟମ ନାହିଁ"
    },
    "answer": "B",
    "explanation": "ମୌଳିକଗୁଡିକର ଗୁଣ ସେଗୁଡ଼ିକର ପାରମାଣବିକ ବସ୍ତୁତ୍ଵର ପର୍ଯ୍ୟାୟ ଫଳନ ।",
    "difficulty": "medium"
  },
  {
    "id": "SCP0523",
    "question": "ମେଣ୍ଡେଲିଫ୍ଙ୍କ ପର୍ଯ୍ୟାୟ ସାରଣୀର ଭୂଲମ୍ବ ସ୍ତମ୍ଭକୁ କ’ଣ କୁହାଯାଏ?",
    "options": {
      "A": "ପର୍ଯ୍ୟାୟ",
      "B": "ସେଲ୍",
      "C": "ଗ୍ରୁପ୍",
      "D": "କକ୍ଷ"
    },
    "answer": "C",
    "explanation": "ଭୂଲମ୍ବ ସ୍ତମ୍ଭକୁ 'ଗ୍ରୁପ' କୁହାଯାଏ ।",
    "difficulty": "easy"
  },
  {
    "id": "SCP0524",
    "question": "ମେଣ୍ଡେଲିଫ୍ଙ୍କ ପର୍ଯ୍ୟାୟ ସାରଣୀର ଭୂସମାନ୍ତର ଧାଡ଼ିକୁ କ’ଣ କୁହାଯାଏ?",
    "options": {
      "A": "ଗ୍ରୁପ୍",
      "B": "ପର୍ଯ୍ୟାୟ",
      "C": "କଲମ୍",
      "D": "ବ୍ଲକ୍"
    },
    "answer": "B",
    "explanation": "ଭୂସମାନ୍ତର ଧାଡ଼ିକୁ 'ପର୍ଯ୍ୟାୟ' କୁହାଯାଏ ।",
    "difficulty": "easy"
  },
  {
    "id": "SCP0525",
    "question": "ମେଣ୍ଡେଲିଫ୍ ପର୍ଯ୍ୟାୟ ସାରଣୀରେ ଖାଲି ସ୍ଥାନ ଛାଡ଼ିଥିବା ଗୋଟିଏ ମୌଳିକର ନାମ କ’ଣ?",
    "options": {
      "A": "ସ୍କାଣ୍ଡିୟମ୍",
      "B": "ଗାଲିୟମ୍",
      "C": "ଜର୍ମାନିୟମ୍",
      "D": "ଉପରୋକ୍ତ ସମସ୍ତ"
    },
    "answer": "D",
    "explanation": "ସ୍କାଣ୍ଡିୟମ୍, ଗାଲିୟମ୍ ଓ ଜର୍ମାନିୟମର ଆବିଷ୍କାର ପାଇଁ ସେ ଖାଲି ସ୍ଥାନ ରଖିଥିଲେ ।",
    "difficulty": "medium"
  },
  {
    "id": "SCP0526",
    "question": "ମେଣ୍ଡେଲିଫ୍ ଗାଲିୟମ୍ ପାଇଁ କେଉଁ ନାମ ବ୍ୟବହାର କରିଥିଲେ?",
    "options": {
      "A": "ଏକ-ବୋରନ",
      "B": "ଏକ-ଏଲୁମିନିୟମ",
      "C": "ଏକ-ସିଲିକନ୍",
      "D": "ଏକ-କାର୍ବନ"
    },
    "answer": "B",
    "explanation": "ଗାଲିୟମର ପୂର୍ବ ନାମ ସେ 'ଏକ-ଏଲୁମିନିୟମ' ଦେଇଥିଲେ ।",
    "difficulty": "hard"
  },
  {
    "id": "SCP0527",
    "question": "ମେଣ୍ଡେଲିଫ୍ଙ୍କ ପର୍ଯ୍ୟାୟ ସାରଣୀର ଗୋଟିଏ ତ୍ରୁଟି କ’ଣ ଥିଲା?",
    "options": {
      "A": "ହାଇଡ୍ରୋଜେନର ସଠିକ ସ୍ଥାନ ନାହିଁ",
      "B": "ଅଧିକ ମୌଳିକ ନଥିଲା",
      "C": "ରଙ୍ଗ ନଥିଲା",
      "D": "ଗ୍ରୁପ୍ କମ୍ ଥିଲା"
    },
    "answer": "A",
    "explanation": "ସେ ହାଇଡ୍ରୋଜେନର ଏକ ସଠିକ ସ୍ଥାନ ସ୍ଥିର କରିପାରିଲେ ନାହିଁ ।",
    "difficulty": "medium"
  },
  {
    "id": "SCP0528",
    "question": "ଆଧୁନିକ ପର୍ଯ୍ୟାୟ ସାରଣୀ କେଉଁ ମୂଳସୂତ୍ର ଉପରେ ପ୍ରତିଷ୍ଠିତ?",
    "options": {
      "A": "ପାରମାଣବିକ ବସ୍ତୁତ୍ଵ",
      "B": "ପରମାଣୁ କ୍ରମାଙ୍କ",
      "C": "ନିଉଟ୍ରନ୍ ସଂଖ୍ୟା",
      "D": "ଇଲେକ୍ଟ୍ରନ୍ ସଂଖ୍ୟା"
    },
    "answer": "B",
    "explanation": "ପରମାଣୁ କ୍ରମାଙ୍କକୁ ଆଧୁନିକ ପର୍ଯ୍ୟାୟ ସାରଣୀର ମୂଳସୂତ୍ର ରୂପେ ଗ୍ରହଣ କରାଗଲା ।",
    "difficulty": "easy"
  },
  {
    "id": "SCP0529",
    "question": "ହେନ୍ରୀ ମୋସଲୀ କେଉଁ ମସିହାରେ ପରମାଣୁ କ୍ରମାଙ୍କର ଗୁରୁତ୍ଵ ଦର୍ଶାଇଥିଲେ?",
    "options": {
      "A": "୧୮୭୨",
      "B": "୧୯୦୦",
      "C": "୧୯୧୩",
      "D": "୧୯୩୦"
    },
    "answer": "C",
    "explanation": "ହେନ୍ରୀ ମୋସଲୀ ୧୯୧୩ ମସିହାରେ ଏହା ଦର୍ଶାଇଥିଲେ ।",
    "difficulty": "hard"
  },
  {
    "id": "SCP0530",
    "question": "ଆଧୁନିକ ପର୍ଯ୍ୟାୟ ସାରଣୀରେ କେତୋଟି ଗ୍ରୁପ୍ ଓ ପର୍ଯ୍ୟାୟ ରହିଛି?",
    "options": {
      "A": "୮ ଗ୍ରୁପ୍, ୭ ପର୍ଯ୍ୟାୟ",
      "B": "୧୮ ଗ୍ରୁପ୍, ୭ ପର୍ଯ୍ୟାୟ",
      "C": "୭ ଗ୍ରୁପ୍, ୧୮ ପର୍ଯ୍ୟାୟ",
      "D": "୧୦ ଗ୍ରୁପ୍, ୧୦ ପର୍ଯ୍ୟାୟ"
    },
    "answer": "B",
    "explanation": "ଆଧୁନିକ ପର୍ଯ୍ୟାୟ ସାରଣୀରେ ୧୮ଟି ଗ୍ରୁପ ଏବଂ ୭ଟି ପର୍ଯ୍ୟାୟ ରହିଛି ।",
    "difficulty": "easy"
  },
  {
    "id": "SCP0531",
    "question": "ଗୋଟିଏ ଗ୍ରୁପ୍ର ମୌଳିକଗୁଡ଼ିକର କ’ଣ ସମାନ ଥାଏ?",
    "options": {
      "A": "ପରମାଣୁ କ୍ରମାଙ୍କ",
      "B": "କକ୍ଷ ସଂଖ୍ୟା",
      "C": "ସଂଯୋଜକ ଇଲେକ୍ଟ୍ରନ୍ ସଂଖ୍ୟା",
      "D": "ପାରମାଣବିକ ବସ୍ତୁତ୍ଵ"
    },
    "answer": "C",
    "explanation": "ଏକା ଗ୍ରୁପରେ ଥିବା ମୌଳିକଗୁଡ଼ିକରେ ସମାନ ସଂଖ୍ୟକ ସଂଯୋଜକ ଇଲେକ୍ଟ୍ରନ ରହିଛି ।",
    "difficulty": "medium"
  },
  {
    "id": "SCP0532",
    "question": "ଗୋଟିଏ ପର୍ଯ୍ୟାୟର ମୌଳିକଗୁଡ଼ିକର କ’ଣ ସମାନ ଥାଏ?",
    "options": {
      "A": "ଯୋଜ୍ୟତା",
      "B": "କକ୍ଷ ସଂଖ୍ୟା",
      "C": "ଇଲେକ୍ଟ୍ରନ୍ ସଂଖ୍ୟା",
      "D": "ଧାତବ ଗୁଣ"
    },
    "answer": "B",
    "explanation": "ଏକା ପର୍ଯ୍ୟାୟରେ ଥିବା ମୌଳିକଗୁଡ଼ିକରେ ସମାନ ସଂଖ୍ୟକ କକ୍ଷ (Shells) ରହିଛି ।",
    "difficulty": "medium"
  },
  {
    "id": "SCP0533",
    "question": "ଦ୍ଵିତୀୟ ପର୍ଯ୍ୟାୟର ମୌଳିକଗୁଡ଼ିକର କେତୋଟି କକ୍ଷ ଥାଏ?",
    "options": {
      "A": "୧",
      "B": "୨",
      "C": "୩",
      "D": "୪"
    },
    "answer": "B",
    "explanation": "ଦ୍ଵିତୀୟ ପର୍ଯ୍ୟାୟରେ କେବଳ K ଓ L କକ୍ଷରେ ଇଲେକ୍ଟ୍ରନ୍ ଭତ୍ତିର୍ ହୁଏ ।",
    "difficulty": "medium"
  },
  {
    "id": "SCP0534",
    "question": "ପର୍ଯ୍ୟାୟ ସାରଣୀରେ ବାମରୁ ଡାହାଣକୁ ଗଲେ ପରମାଣୁର ବ୍ୟାସାର୍ଦ୍ଧ କିପରି ବଦଳେ?",
    "options": {
      "A": "ବଢେ",
      "B": "କ୍ରମାଗତ କମେ",
      "C": "ଅପରିବର୍ତ୍ତିତ ରହେ",
      "D": "ପ୍ରଥମେ କମେ ପରେ ବଢେ"
    },
    "answer": "B",
    "explanation": "ନୁ୍ୟକ୍ଲିୟସର ବଦ୍ଧିର୍ତ ଚାର୍ଜ ଯୋଗୁଁ ଆକାର କ୍ରମାଗତ ଭାବେ କମେ ।",
    "difficulty": "medium"
  },
  {
    "id": "SCP0535",
    "question": "ଗ୍ରୁପ୍ରେ ଉପରୁ ତଳକୁ ଗଲେ ପରମାଣୁର ଆକାର କିପରି ବଦଳେ?",
    "options": {
      "A": "କମେ",
      "B": "ବଢେ",
      "C": "ସମାନ ରହେ",
      "D": "ଶୂନ୍ୟ ହୋଇଯାଏ"
    },
    "answer": "B",
    "explanation": "ନୂଆ କକ୍ଷ ଯୋଗ ହେବା ଫଳରେ ପରମାଣୁ ଆକାର ବଢ଼ିଥାଏ ।",
    "difficulty": "medium"
  },
  {
    "id": "SCP0536",
    "question": "ପର୍ଯ୍ୟାୟ ସାରଣୀରେ ଧାତୁଗୁଡ଼ିକ ସାଧାରଣତଃ କେଉଁ ପାଶ୍ଵର୍ରେ ରହିଥାନ୍ତି?",
    "options": {
      "A": "ଡାହାଣ",
      "B": "ବାମ",
      "C": "ଶେଷ",
      "D": "ଉପର"
    },
    "answer": "B",
    "explanation": "ଧାତୁଗୁଡ଼ିକ ସାଧାରଣତଃ ବାମ ପାଶ୍ଵର୍ରେ ଦେଖାଯାନ୍ତି ।",
    "difficulty": "easy"
  },
  {
    "id": "SCP0537",
    "question": "ନିମ୍ନଲିଖିତ ମଧ୍ୟରୁ କେଉଁଟି ଏକ ଉପଧାତୁ ବା ଅର୍ଦ୍ଧଧାତୁ?",
    "options": {
      "A": "ସୋଡ଼ିୟମ୍",
      "B": "ସିଲିକନ୍",
      "C": "କାର୍ବନ୍",
      "D": "ଲୁହା"
    },
    "answer": "B",
    "explanation": "ସିଲିକନ୍ ଉଭୟ ଧାତୁ ଓ ଅଧାତୁର ଗୁଣ ଦର୍ଶାଉଥିବାରୁ ଏହା ଉପଧାତୁ ।",
    "difficulty": "medium"
  },
  {
    "id": "SCP0538",
    "question": "ପର୍ଯ୍ୟାୟରେ ବାମରୁ ଡାହାଣକୁ ଗଲେ ଧାତବ ପ୍ରକୃତି କିପରି ପରିବର୍ତ୍ତନ ହୁଏ?",
    "options": {
      "A": "ବଢେ",
      "B": "କମେ",
      "C": "ସମାନ ରହେ",
      "D": "ଦୁଇଗୁଣ ହୁଏ"
    },
    "answer": "B",
    "explanation": "ଇଲେକ୍ଟ୍ରନ୍ ତ୍ୟାଗ କରିବା କଷ୍ଟକର ହେଉଥିବାରୁ ଧାତବ ପ୍ରକୃତି କମିଯାଏ ।",
    "difficulty": "hard"
  },
  {
    "id": "SCP0539",
    "question": "ଗ୍ରୁପ୍ରେ ଉପରୁ ତଳକୁ ଗଲେ ଧାତବ ପ୍ରକୃତି କ’ଣ ହୁଏ?",
    "options": {
      "A": "ବୃଦ୍ଧିପାଏ",
      "B": "କମେ",
      "C": "ସମାନ ରହେ",
      "D": "ଅସ୍ଥାୟୀ ହୁଏ"
    },
    "answer": "A",
    "explanation": "କକ୍ଷ ସଂଖ୍ୟା ବଢ଼ିବା ଯୋଗୁଁ ଇଲେକ୍ଟ୍ରନ୍ ହରାଇବା ସହଜ ହୁଏ, ତେଣୁ ଧାତବ ପ୍ରକୃତି ବଢ଼େ ।",
    "difficulty": "hard"
  },
  {
    "id": "SCP0540",
    "question": "ଅଧାତବ ଅକ୍ସାଇଡ୍ର ପ୍ରକୃତି କିପରି?",
    "options": {
      "A": "କ୍ଷାରୀୟ",
      "B": "ଅମ୍ଳୀୟ",
      "C": "ପ୍ରଶମିତ",
      "D": "ଲବଣାକ୍ତ"
    },
    "answer": "B",
    "explanation": "ସାଧାରଣତଃ ଅଧାତୁର ଅକ୍ସାଇଡ୍ଗୁଡ଼ିକ ଅମ୍ଳୀୟ ହୋଇଥାଏ ।",
    "difficulty": "medium"
  },
  {
    "id": "SCP0541",
    "question": "ଧାତବ ଅକ୍ସାଇଡ୍ର ପ୍ରକୃତି ସାଧାରଣତଃ କିପରି?",
    "options": {
      "A": "ଅମ୍ଳୀୟ",
      "B": "କ୍ଷାରୀୟ",
      "C": "ପ୍ରଶମିତ",
      "D": "ତିକ୍ତ"
    },
    "answer": "B",
    "explanation": "ସାଧାରଣତଃ ଧାତୁର ଅକ୍ସାଇଡ୍ଗୁଡ଼ିକ କ୍ଷାରୀୟ ହୋଇଥାଏ ।",
    "difficulty": "medium"
  },
  {
    "id": "SCP0542",
    "question": "ପର୍ଯ୍ୟାୟ ସାରଣୀରେ ଅଧାତୁଗୁଡ଼ିକ କେଉଁ ପାଶ୍ଵର୍ରେ ଦେଖାଯାଏ?",
    "options": {
      "A": "ବାମ",
      "B": "ଡାହାଣ ପାଶ୍ଵର୍ର ଉପର ଆଡ଼କୁ",
      "C": "ମଝିରେ",
      "D": "ତଳେ"
    },
    "answer": "B",
    "explanation": "ଅଧାତୁଗୁଡ଼ିକ ପର୍ଯ୍ୟାୟ ସାରଣୀର ଦକ୍ଷିଣ ପାଶ୍ଵର୍ର ଉପର ଆଡକୁ ଦେଖାଯାଏ ।",
    "difficulty": "hard"
  },
  {
    "id": "SCP0543",
    "question": "ସ୍ପଷ୍ଟ ଦର୍ଶନର ସର୍ବନିମ୍ନ ଦୂରତା କେତେ?",
    "options": {
      "A": "୨.୫ ସେମି",
      "B": "୨୫ ମିଟର",
      "C": "୨୫ ସେମି",
      "D": "ଅନନ୍ତ"
    },
    "answer": "C",
    "explanation": "ସାଧାରଣ ଚ଼କ୍ଷୁ ପାଇଁ ସର୍ବନିମ୍ନ ଦୂରତା ୨୫ ସେମି ଅଟେ ।",
    "difficulty": "easy"
  },
  {
    "id": "SCP0544",
    "question": "ମେଣ୍ଡେଲିଫ୍ଙ୍କ ପର୍ଯ୍ୟାୟ ସାରଣୀ କେବେ ପ୍ରକାଶ ପାଇଥିଲା?",
    "options": {
      "A": "୧୮୧୭",
      "B": "୧୮୬୬",
      "C": "୧୮୭୨",
      "D": "୧୯୧୩"
    },
    "answer": "C",
    "explanation": "ଏହା ୧୮୭୨ ମସିହାରେ ଜର୍ମାନୀର ଏକ ପତ୍ରିକାରେ ପ୍ରକାଶ ପାଇଥିଲା ।",
    "difficulty": "hard"
  },
  {
    "id": "SCP0545",
    "question": "ସମାନ ପାରମାଣବିକ କ୍ରମାଙ୍କ କିନ୍ତୁ ଭିନ୍ନ ବସ୍ତୁତ୍ଵ ସଂଖ୍ୟା ଥିବା ପରମାଣୁକୁ କ’ଣ କୁହାଯାଏ?",
    "options": {
      "A": "ଆଇସୋଟୋପ୍",
      "B": "ଆଇସୋମର୍",
      "C": "ଆଇସୋବାର୍",
      "D": "ହୋମୋଲଗସ୍"
    },
    "answer": "A",
    "explanation": "ଏହାକୁ ଆଇସୋଟୋପ୍ କୁହାଯାଏ ।",
    "difficulty": "medium"
  },
  {
    "id": "SCP0546",
    "question": "ନିଉଲାଣ୍ଡଙ୍କ ଅଷ୍ଟକ ନିୟମ କେଉଁ ମୌଳିକଗୁଡ଼ିକ ପାଇଁ ଠିକ୍ କାର୍ଯ୍ୟ କଲା?",
    "options": {
      "A": "ଭାରୀ ମୌଳିକ",
      "B": "ହାଲୁକା ମୌଳିକ",
      "C": "ଗ୍ୟାସୀୟ ମୌଳିକ",
      "D": "ମିଶ୍ରଧାତୁ"
    },
    "answer": "B",
    "explanation": "ଏହା କେବଳ ହାଲୁକା ମୌଳିକଗୁଡ଼ିକ ପାଇଁ ଠିକ୍ କାର୍ଯ୍ୟ କଲା ।",
    "difficulty": "medium"
  },
  {
    "id": "SCP0547",
    "question": "ଆଧୁନିକ ପର୍ଯ୍ୟାୟ ସାରଣୀରେ କେଉଁ ରେଖା ଧାତୁକୁ ଅଧାତୁଠାରୁ ପୃଥକ୍ କରେ?",
    "options": {
      "A": "ସଳଖ ରେଖା",
      "B": "ବଙ୍କା-ଟଙ୍କା ରେଖା",
      "C": "ଭୂଲମ୍ବ ରେଖା",
      "D": "ଭୂସମାନ୍ତର ରେଖା"
    },
    "answer": "B",
    "explanation": "ଏକ ବଙ୍କା-ଟଙ୍କା ରେଖା ଅଧାତୁଠାରୁ ଧାତୁକୁ ପୃଥକ୍ କରିଥାଏ ।",
    "difficulty": "medium"
  },
  {
    "id": "SCP0548",
    "question": "ମୌଳିକର ଯୋଜ୍ୟତା କାହା ଦ୍ଵାରା ନିରୂପଣ କରାଯାଏ?",
    "options": {
      "A": "ପ୍ରୋଟନ ସଂଖ୍ୟା",
      "B": "ନିଉଟ୍ରନ ସଂଖ୍ୟା",
      "C": "ସଂଯୋଜକ ଇଲେକ୍ଟ୍ରନ୍ ସଂଖ୍ୟା",
      "D": "ଆଣବିକ ଓଜନ"
    },
    "answer": "C",
    "explanation": "ବାହ୍ୟତମ କକ୍ଷରେ ଥିବା ସଂଯୋଜକ ଇଲେକ୍ଟ୍ରନ୍ ସଂଖ୍ୟା ଦ୍ଵାରା ଯୋଜ୍ୟତା ନିର୍ଣ୍ଣୟ ହୁଏ ।",
    "difficulty": "easy"
  },
  {
    "id": "SCP0549",
    "question": "ମେଣ୍ଡେଲିଫ୍ଙ୍କ ପର୍ଯ୍ୟାୟ ସାରଣୀରେ ସଙ୍କେତ ‘R’ କାହାକୁ ସୂଚାଏ?",
    "options": {
      "A": "ରେଡିୟମ୍",
      "B": "ଗ୍ରୁପର ଯେକୌଣସି ମୌଳିକ",
      "C": "ଅକ୍ସିଜେନ୍",
      "D": "ନାଇଟ୍ରୋଜେନ୍"
    },
    "answer": "B",
    "explanation": "‘ଜ’ ବା 'R' ଅକ୍ଷର ସେହି ଗ୍ରୁପର ଯେକୌଣସି ମୌଳିକକୁ ସୂଚାଇବା ପାଇଁ ବ୍ୟବହୃତ ।",
    "difficulty": "hard"
  },
  {
    "id": "SCP0550",
    "question": "ମୌଳିକର ଗୁଣଗୁଡ଼ିକ ପରମାଣୁ କ୍ରମାଙ୍କର ପର୍ଯ୍ୟାୟ ଫଳନ - ଏହା କେଉଁ ନିୟମ?",
    "options": {
      "A": "ଡୁବେରିନର ନିୟମ",
      "B": "ମେଣ୍ଡେଲିଫ୍ଙ୍କ ନିୟମ",
      "C": "ଆଧୁନିକ ପର୍ଯ୍ୟାୟ ନିୟମ",
      "D": "ଅଷ୍ଟକ ନିୟମ"
    },
    "answer": "C",
    "explanation": "ଏହା ହେଉଛି ଆଧୁନିକ ପର୍ଯ୍ୟାୟ ନିୟମ ।",
    "difficulty": "easy"
  },
  {
    "id": "SCP0551",
    "question": "ନିଉଲାଣ୍ଡଙ୍କ ସାରଣୀରେ କୋବାଲ୍ଟ ଓ ନିକେଲ୍ କେଉଁ ସ୍ତମ୍ଭରେ ରହିଥିଲେ?",
    "options": {
      "A": "Li, Na, K ସହ",
      "B": "F, Cl, Br ସହ",
      "C": "O, S, Se ସହ",
      "D": "Be, Mg, Ca ସହ"
    },
    "answer": "B",
    "explanation": "ସେମାନଙ୍କୁ ଫ୍ଲୋରିନ୍, କ୍ଲୋରିନ୍ ଓ ବ୍ରୋମିନ୍ ଥିବା ସ୍ତମ୍ଭରେ ସ୍ଥାନିତ କରାଯାଇଥିଲା ।",
    "difficulty": "hard"
  },
  {
    "id": "SCP0552",
    "question": "ପାରମାଣବିକ ବ୍ୟାସାର୍ଦ୍ଧ ମାପିବା ପାଇଁ ବ୍ୟବହୃତ ଏକକ ‘pm’ ର ପୂରା ନାମ କ’ଣ?",
    "options": {
      "A": "ପୋଷ୍ଟମିଟର",
      "B": "ପିକୋମିଟର",
      "C": "ପାରାମିଟର",
      "D": "ପିକାସୋମିଟର"
    },
    "answer": "B",
    "explanation": "pm ର ଅର୍ଥ ହେଉଛି ପିକୋମିଟର (10^-12 m) ।",
    "difficulty": "easy"
  },
  {
    "id": "SCP0553",
    "question": "ଆମ ଚାରିପଟେ ଥିବା ବସ୍ତୁଗୁଡ଼ିକ କେଉଁ ରୂପରେ ରହିଥାଏ?",
    "options": {
      "A": "ମୌଳିକ",
      "B": "ଯୌଗିକ",
      "C": "ମିଶ୍ରଣ",
      "D": "ଉପରୋକ୍ତ ସମସ୍ତ"
    },
    "answer": "D",
    "explanation": "ବସ୍ତୁଗୁଡ଼ିକ ମୌଳିକ, ଯୌଗିକ ଏବଂ ମିଶ୍ରଣ ରୂପରେ ରହିଥାଏ ।",
    "difficulty": "easy"
  },
  {
    "id": "SCP0554",
    "question": "ମେଣ୍ଡେଲିଫ୍ଙ୍କ ସାରଣୀରେ କୋବାଲ୍ଟ ଓ ନିକେଲ୍ଙ୍କ ପାରମାଣବିକ ବସ୍ତୁତ୍ଵ ମଧ୍ୟରୁ କାହାର ଅଧିକ ଥିଲା?",
    "options": {
      "A": "ନିକେଲ୍",
      "B": "କୋବାଲ୍ଟ",
      "C": "ଉଭୟଙ୍କ ସମାନ",
      "D": "ଜଣା ନାହିଁ"
    },
    "answer": "B",
    "explanation": "କୋବାଲ୍ଟ (୫୮.୯) ନିକେଲ (୫୮.୭) ଠାରୁ ସାମାନ୍ୟ ଅଧିକ ଥିଲା ।",
    "difficulty": "hard"
  },
  {
    "id": "SCP0555",
    "question": "ହାଇଡ୍ରୋଜେନ ପରମାଣୁର ବ୍ୟାସାର୍ଦ୍ଧ କେତେ ପିକୋମିଟର?",
    "options": {
      "A": "୧୦",
      "B": "୨୫",
      "C": "୩୭",
      "D": "୫୦"
    },
    "answer": "C",
    "explanation": "ହାଇଡ୍ରୋଜେନ ପରମାଣୁର ବ୍ୟାସାର୍ଦ୍ଧ ହେଉଛି ୩୭ pm ।",
    "difficulty": "medium"
  },
  {
    "id": "SCP0556",
    "question": "ନିମ୍ନଲିଖିତ ମଧ୍ୟରୁ କେଉଁଟି ଏକ ହାଲୋଜେନ୍ ନୁହେଁ?",
    "options": {
      "A": "କ୍ଲୋରିନ୍",
      "B": "ବ୍ରୋମିନ୍",
      "C": "ସୋଡ଼ିୟମ୍",
      "D": "ଫ୍ଲୋରିନ୍"
    },
    "answer": "C",
    "explanation": "ସୋଡ଼ିୟମ୍ ଏକ କ୍ଷାରୀୟ ଧାତୁ, ହାଲୋଜେନ୍ ନୁହେଁ ।",
    "difficulty": "easy"
  },
  {
    "id": "SCP0557",
    "question": "ଆଧୁନିକ ପର୍ଯ୍ୟାୟ ସାରଣୀରେ ‘K’ କେତୋଟି ଇଲେକ୍ଟ୍ରନ୍ ଧାରଣ କରିପାରେ?",
    "options": {
      "A": "୨",
      "B": "୮",
      "C": "୧୮",
      "D": "୩୨"
    },
    "answer": "A",
    "explanation": "ପ୍ରଥମ କକ୍ଷ (K) ରେ ସର୍ବାଧିକ ୨ଟି ଇଲେକ୍ଟ୍ରନ୍ ରହିପାରେ ।",
    "difficulty": "medium"
  },
  {
    "id": "SCP0558",
    "question": "ନିକ୍ରୋମ କେଉଁ ମୌଳିକଗୁଡ଼ିକର ଏକ ମିଶ୍ରଧାତୁ?",
    "options": {
      "A": "Cu, Zn",
      "B": "Fe, C",
      "C": "Ni, Cr, Mn, Fe",
      "D": "Sn, Pb"
    },
    "answer": "C",
    "explanation": "ନିକ୍ରୋମ ହେଉଛି ନିକେଲ୍, କ୍ରୋମିୟମ, ମାଙ୍ଗାନିଜ ଓ ଲୌହର ମିଶ୍ରଧାତୁ ।",
    "difficulty": "hard"
  },
  {
    "id": "SCP0559",
    "question": "ପର୍ଯ୍ୟାୟ ସାରଣୀର ଗ୍ରୁପ-୧୭ର ମୌଳିକଗୁଡ଼ିକୁ କ’ଣ କୁହାଯାଏ?",
    "options": {
      "A": "କ୍ଷାର ଧାତୁ",
      "B": "ନୋବଲ୍ ଗ୍ୟାସ୍",
      "C": "ହାଲୋଜେନ୍",
      "D": "ଚାଲ୍କୋଜେନ୍"
    },
    "answer": "C",
    "explanation": "ଗ୍ରୁପ-୧୭ ରେ ଥିବା ମୌଳିକଗୁଡ଼ିକୁ ହାଲୋଜେନ୍ କୁହାଯାଏ ।",
    "difficulty": "medium"
  },
  {
    "id": "SCP0560",
    "question": "ନୋବଲ୍ ଗ୍ୟାସ୍ ଗୁଡ଼ିକ କେଉଁ ଗ୍ରୁପରେ ଅବସ୍ଥିତ?",
    "options": {
      "A": "ଗ୍ରୁପ-୧",
      "B": "ଗ୍ରୁପ-୧୦",
      "C": "ଗ୍ରୁପ-୧୭",
      "D": "ଗ୍ରୁପ-୧୮"
    },
    "answer": "D",
    "explanation": "ନୋବଲ୍ ଗ୍ୟାସ୍ଗୁଡ଼ିକ ଆଧୁନିକ ପର୍ଯ୍ୟାୟ ସାରଣୀର ଶେଷ ଗ୍ରୁପ (୧୮) ରେ ରହିଛି ।",
    "difficulty": "medium"
  },
  {
    "id": "SCP0561",
    "question": "ମେଣ୍ଡେଲିଫ୍ଙ୍କ ସାରଣୀରେ ଅକ୍ସାଇଡ୍ର ସାଧାରଣ ସଙ୍କେତ କିପରି ଦର୍ଶାଯାଇଥିଲା?",
    "options": {
      "A": "MO",
      "B": "RO",
      "C": "XO",
      "D": "AO"
    },
    "answer": "B",
    "explanation": "ସେ ଅକ୍ସାଇଡ୍ ପାଇଁ 'R' ବା 'ଜ' ଅକ୍ଷର ବ୍ୟବହାର କରିଥିଲେ ।",
    "difficulty": "hard"
  },
  {
    "id": "SCP0562",
    "question": "ନିମ୍ନଲିଖିତ ମଧ୍ୟରୁ କାହାର ପରମାଣୁ ଆକାର ସର୍ବାଧିକ?",
    "options": {
      "A": "Li",
      "B": "Na",
      "C": "K",
      "D": "Cs"
    },
    "answer": "D",
    "explanation": "ଗ୍ରୁପ୍ରେ ଉପରୁ ତଳକୁ ଗଲେ Cs ର ଆକାର ସବୁଠାରୁ ବଡ଼ ।",
    "difficulty": "hard"
  },
  {
    "id": "SCP0563",
    "question": "ମୌଳିକର ପ୍ରତିକ୍ରିୟାଶୀଳତା କେଉଁ କଣିକା ଉପରେ ନିର୍ଭର କରେ?",
    "options": {
      "A": "ପ୍ରୋଟନ୍",
      "B": "ନିଉଟ୍ରନ୍",
      "C": "ସଂଯୋଜକ ଇଲେକ୍ଟ୍ରନ୍",
      "D": "କେନ୍ଦ୍ରକ"
    },
    "answer": "C",
    "explanation": "ସଂଯୋଜକ ଇଲେକ୍ଟ୍ରନ ମୌଳିକର ପ୍ରତିକ୍ରିୟାଶୀଳତା ନିରୂପଣ କରେ ।",
    "difficulty": "medium"
  },
  {
    "id": "SCP0564",
    "question": "ପର୍ଯ୍ୟାୟ ସାରଣୀର ଗ୍ରୁପ-୧କୁ କ’ଣ କୁହାଯାଏ?",
    "options": {
      "A": "କ୍ଷାର ଧାତୁ",
      "B": "କ୍ଷାରୀୟ ମୃତ୍ତିକା ଧାତୁ",
      "C": "ହାଲୋଜେନ୍",
      "D": "ନିଷ୍କ୍ରିୟ ଗ୍ୟାସ୍"
    },
    "answer": "A",
    "explanation": "ଗ୍ରୁପ-୧ ର ମୌଳିକଗୁଡ଼ିକୁ କ୍ଷାର ଧାତୁ (Alkali metals) କୁହାଯାଏ ।",
    "difficulty": "medium"
  },
  {
    "id": "SCP0565",
    "question": "ବୋରନ୍, ସିଲିକନ୍ ଓ ଜର୍ମାନିୟମ୍ ଗୁଡ଼ିକ କ’ଣ?",
    "options": {
      "A": "ଧାତୁ",
      "B": "ଅଧାତୁ",
      "C": "ଉପଧାତୁ",
      "D": "ନିଷ୍କ୍ରିୟ ଗ୍ୟାସ୍"
    },
    "answer": "C",
    "explanation": "ଏଗୁଡ଼ିକ ଉଭୟ ଧାତୁ ଓ ଅଧାତୁର ଗୁଣ ଦର୍ଶାଉଥିବାରୁ ଉପଧାତୁ ।",
    "difficulty": "medium"
  },
  {
    "id": "SCP0566",
    "question": "ଇଲେକ୍ଟ୍ରନ୍ ଗ୍ରହଣ କରିବା ପ୍ରବୃତ୍ତିକୁ କ’ଣ କୁହାଯାଏ?",
    "options": {
      "A": "ବିଦୁ୍ୟତ୍ ଯୁକ୍ତାତ୍ମକତା",
      "B": "ବିଦୁ୍ୟତ୍ ବିଯୁକ୍ତାତ୍ମକତା",
      "C": "ଜାରଣ",
      "D": "ପରିବାହିତା"
    },
    "answer": "B",
    "explanation": "ଅଧାତୁଗୁଡ଼ିକ ଇଲେକ୍ଟ୍ରନ୍ ଗ୍ରହଣ କରୁଥିବାରୁ ସେମାନେ ବିଦୁ୍ୟତ୍ ବିଯୁକ୍ତାତ୍ମକ ।",
    "difficulty": "hard"
  },
  {
    "id": "SCP0567",
    "question": "ଗୋଟିଏ ଗ୍ରୁପ୍ରେ ଉପରୁ ତଳକୁ ଗଲେ ବିଦୁ୍ୟତ୍ ବିଯୁକ୍ତାତ୍ମକତା କ’ଣ ହୁଏ?",
    "options": {
      "A": "ବଢେ",
      "B": "କମେ",
      "C": "ସମାନ ରହେ",
      "D": "ଶୂନ୍ୟ ହୁଏ"
    },
    "answer": "B",
    "explanation": "ଆକାର ବୃଦ୍ଧି ଯୋଗୁଁ ଇଲେକ୍ଟ୍ରନ୍ ଗ୍ରହଣ କରିବା ପ୍ରବୃତ୍ତି କମିଯାଏ ।",
    "difficulty": "hard"
  },
  {
    "id": "SCP0568",
    "question": "ମେଣ୍ଡେଲିଫ୍ଙ୍କ ସାରଣୀରେ ସଲ୍ଫର୍ କେଉଁ ଗ୍ରୁପ୍ରେ ଅଛି?",
    "options": {
      "A": "VI",
      "B": "IV",
      "C": "II",
      "D": "VIII"
    },
    "answer": "A",
    "explanation": "ସଲ୍ଫର୍ ଗ୍ରୁପ VI ର ଅନ୍ତଭୁର୍କ୍ତ ।",
    "difficulty": "hard"
  },
  {
    "id": "SCP0569",
    "question": "ଆଧୁନିକ ପର୍ଯ୍ୟାୟ ସାରଣୀର ପ୍ରଥମ ପର୍ଯ୍ୟାୟରେ କେତୋଟି ମୌଳିକ ଅଛି?",
    "options": {
      "A": "୨",
      "B": "୮",
      "C": "୧୮",
      "D": "୩୨"
    },
    "answer": "A",
    "explanation": "ପ୍ରଥମ ପର୍ଯ୍ୟାୟରେ କେବଳ ହାଇଡ୍ରୋଜେନ୍ ଓ ହିଲିୟମ୍ ରହିଛି ।",
    "difficulty": "medium"
  },
  {
    "id": "SCP0570",
    "question": "ସୂର୍ଯ୍ୟାଲୋକରେ ସିଲ୍ଭର୍ କ୍ଲୋରାଇଡ୍ କେଉଁ ରଙ୍ଗରେ ପରିଣତ ହୁଏ?",
    "options": {
      "A": "ନାଲି",
      "B": "ଧୂସର",
      "C": "ହଳଦିଆ",
      "D": "ଧଳା"
    },
    "answer": "B",
    "explanation": "ଏହା ବିଘଟିତ ହୋଇ ଧୂସର ରଙ୍ଗର ସିଲ୍ଭର୍ ଧାତୁ ଦିଏ ।",
    "difficulty": "easy"
  },
  {
    "id": "SCP0571",
    "question": "ମୌଳିକର ଆଇସୋଟୋପଗୁଡିକର କ’ଣ ସମାନ ଥାଏ?",
    "options": {
      "A": "ବସ୍ତୁତ୍ଵ ସଂଖ୍ୟା",
      "B": "ରାସାୟନିକ ପ୍ରକୃତି",
      "C": "ପାରମାଣବିକ ବସ୍ତୁତ୍ଵ",
      "D": "ଉଭୟ A ଓ C"
    },
    "answer": "B",
    "explanation": "ସେମାନଙ୍କର ରାସାୟନିକ ପ୍ରକୃତି ସମାନ ଥାଏ ।",
    "difficulty": "medium"
  },
  {
    "id": "SCP0572",
    "question": "ଲିଥିୟମ୍ ପରେ ଅଷ୍ଟମ ମୌଳିକଟି କିଏ?",
    "options": {
      "A": "ସୋଡ଼ିୟମ୍",
      "B": "ପୋଟାସିୟମ୍",
      "C": "ମ୍ୟାଗ୍ନେସିୟମ୍",
      "D": "ବେରିଲିୟମ୍"
    },
    "answer": "A",
    "explanation": "ଲିଥିୟମ୍ ପରେ ସୋଡ଼ିୟମ ହେଉଛି ଅଷ୍ଟମ ମୌଳିକ (ନିଉଲାଣ୍ଡଙ୍କ ଅନୁସାରେ) ।",
    "difficulty": "medium"
  },
  {
    "id": "SCP0573",
    "question": "ଫୋକସ୍ ଦୂରତା ମିଟରରେ ଥିଲେ ପାଓ୍ଵାରର ଏକକ କ’ଣ ହୁଏ?",
    "options": {
      "A": "ଓ୍ଵାଟ୍",
      "B": "ଜୁଲ୍",
      "C": "ଡାୟପ୍ଟର",
      "D": "ଓମ୍"
    },
    "answer": "C",
    "explanation": "ଲେନ୍ସର ପାଓ୍ଵାରର ଏକକ ହେଉଛି ଡାୟପ୍ଟର ।",
    "difficulty": "easy"
  },
  {
    "id": "SCP0574",
    "question": "ସକ୍ରିୟତା ଅନୁକ୍ରମରେ ସବୁଠାରୁ କମ୍ ପ୍ରତିକ୍ରିୟାଶୀଳ ଧାତୁ କେଉଁଟି?",
    "options": {
      "A": "ଲୁହା",
      "B": "ତମ୍ବା",
      "C": "ସୁନା",
      "D": "ସୋଡ଼ିୟମ୍"
    },
    "answer": "C",
    "explanation": "ସୁନା (Au) ସବୁଠାରୁ କମ୍ ପ୍ରତିକ୍ରିୟାଶୀଳ ।",
    "difficulty": "easy"
  },
  {
    "id": "SCP0575",
    "question": "ପର୍ଯ୍ୟାୟ ସାରଣୀରେ ଅଧିକ ପ୍ରତିକ୍ରିୟାଶୀଳତା କିପରି ସୂଚିତ ହୁଏ?",
    "options": {
      "A": "ବାହ୍ୟତମ କକ୍ଷ ଶୀଘ୍ର ପୂର୍ଣ୍ଣ ହେବା",
      "B": "ଆକାର ବଡ଼ ହେବା",
      "C": "ଓଜନ ବଢିବା",
      "D": "ନଷ୍ଟ ହେବା"
    },
    "answer": "A",
    "explanation": "ବାହ୍ୟତମ କକ୍ଷ ପୂର୍ଣ୍ଣ କରିବା ପାଇଁ ଇଲେକ୍ଟ୍ରନ୍ ଗ୍ରହଣ ବା ତ୍ୟାଗ କରିବା ପ୍ରବୃତ୍ତି ସକ୍ରିୟତାକୁ ସୂଚାଏ ।",
    "difficulty": "hard"
  }
]
}
