{
  "questions": [
    {
      "id": "FLO0201",
      "question": "‘ରାଘବଙ୍କ ଲଙ୍କା ଯାତ୍ରାନୁକୂଳ’ କବିତାର କବି କିଏ?",
      "options": {
        "A": "ସାରଳା ଦାସ",
        "B": "ଉପେନ୍ଦ୍ର ଭଞ୍ଜ",
        "C": "ରାଧାନାଥ ରାୟ",
        "D": "ଗଙ୍ଗାଧର ମେହେର"
      },
      "answer": "B",
      "explanation": "କବିସମ୍ରାଟ ଉପେନ୍ଦ୍ର ଭଞ୍ଜ ଏହି କବିତାର ରଚୟିତା।",
      "difficulty": "easy"
    },
    {
      "id": "FLO0202",
      "question": "ଉପେନ୍ଦ୍ର ଭଞ୍ଜ କେଉଁ ରାଜବଂଶରେ ଜନ୍ମଗ୍ରହଣ କରିଥିଲେ?",
      "options": {
        "A": "ଗଜପତି ରାଜବଂଶ",
        "B": "ଘୁମୁସର ରାଜବଂଶ",
        "C": "ଭଞ୍ଜନଗର ରାଜବଂଶ",
        "D": "ସୂର୍ଯ୍ୟବଂଶ"
      },
      "answer": "B",
      "explanation": "ସେ ଘୁମୁସର ରାଜବଂଶରେ ଜନ୍ମଗ୍ରହଣ କରିଥିଲେ।",
      "difficulty": "easy"
    },
    {
      "id": "FLO0203",
      "question": "ଉପେନ୍ଦ୍ର ଭଞ୍ଜ କେଉଁ ମନ୍ତ୍ର ଜପ କରି କବିତ୍ଵ ଶକ୍ତି ଲାଭ କରିଥିଲେ?",
      "options": {
        "A": "ଗାୟତ୍ରୀ ମନ୍ତ୍ର",
        "B": "ଶିବ ପଞ୍ଚାକ୍ଷର ମନ୍ତ୍ର",
        "C": "ରାମ ତାରକ ମନ୍ତ୍ର",
        "D": "ଓଁ ନମୋ ଭଗବତେ ବାସୁଦେବାୟ"
      },
      "answer": "C",
      "explanation": "ରାମ ତାରକ ମନ୍ତ୍ର ଜପ କରି ସେ କବିତ୍ଵ ଶକ୍ତି ପ୍ରାପ୍ତ କରିଥିଲେ।",
      "difficulty": "medium"
    },
    {
      "id": "FLO0204",
      "question": "‘ରାଘବଙ୍କ ଲଙ୍କା ଯାତ୍ରାନୁକୂଳ’ କବିତାଟି କେଉଁ କାବ୍ୟର ଅଂଶବିଶେଷ?",
      "options": {
        "A": "ଲାବଣ୍ୟବତୀ",
        "B": "କୋଟିବ୍ରହ୍ମାଣ୍ଡ ସୁନ୍ଦରୀ",
        "C": "ବୈଦେହୀଶ ବିଳାସ",
        "D": "ପ୍ରେମ ସୁଧାନିଧି"
      },
      "answer": "C",
      "explanation": "ଏହା ଉପେନ୍ଦ୍ର ଭଞ୍ଜଙ୍କ ପ୍ରସିଦ୍ଧ ‘ବୈଦେହୀଶ ବିଳାସ’ କାବ୍ୟରୁ ଆନୀତ।",
      "difficulty": "easy"
    },
    {
      "id": "FLO0205",
      "question": "‘ବୈଦେହୀଶ ବିଳାସ’ କାବ୍ୟଟି କେତୋଟି ଛାନ୍ଦ ବିଶିଷ୍ଟ?",
      "options": {
        "A": "୪୦",
        "B": "୫୨",
        "C": "୧୦୦",
        "D": "୩୨"
      },
      "answer": "B",
      "explanation": "ଏହି କାବ୍ୟଟି ମୋଟ ୫୨ଟି ଛାନ୍ଦରେ ରଚିତ।",
      "difficulty": "medium"
    },
    {
      "id": "FLO0206",
      "question": "ଏହି କବିତାରେ ପ୍ରତ୍ୟେକ ପଦ କେଉଁ ଅକ୍ଷରରେ ଆରମ୍ଭ ହୋଇଛି?",
      "options": {
        "A": "ର",
        "B": "ସ",
        "C": "ବ",
        "D": "କ"
      },
      "answer": "C",
      "explanation": "ନିୟମ ଅନୁସାରେ ଏହି କାବ୍ୟର ପ୍ରତ୍ୟେକ ପଦ ‘ବ’ ଆଦ୍ୟ ବର୍ଣ୍ଣରେ ରଚିତ।",
      "difficulty": "medium"
    },
    {
      "id": "FLO0207",
      "question": "ସୀତାଙ୍କୁ ଉଦ୍ଧାର କରିବା ପାଇଁ ରାମଚନ୍ଦ୍ର କ’ଣ ପୋତିବାକୁ ସ୍ଥିର କଲେ?",
      "options": {
        "A": "ନଦୀ",
        "B": "ପୋଖରୀ",
        "C": "ସିନ୍ଧୁ (ସମୁଦ୍ର)",
        "D": "ଗାଡ଼ିଆ"
      },
      "answer": "C",
      "explanation": "ରାମଚନ୍ଦ୍ର ସମୁଦ୍ର ବା ସିନ୍ଧୁକୁ ପର୍ବତରେ ପୋତିବାକୁ ବିଚାର କରିଥିଲେ।",
      "difficulty": "easy"
    },
    {
      "id": "FLO0208",
      "question": "ସିନ୍ଧୁ ପୋତିବା ପାଇଁ କପିମାନେ କ’ଣ ପକାଉଥିଲେ?",
      "options": {
        "A": "କାଠ",
        "B": "ବାଲି",
        "C": "ଗିରି (ପର୍ବତ)",
        "D": "ଲୁହା"
      },
      "answer": "C",
      "explanation": "ସେତୁ ବାନ୍ଧିବା ପାଇଁ କପିମାନେ ପର୍ବତ ବା ଗିରି ପକାଉଥିଲେ।",
      "difficulty": "easy"
    },
    {
      "id": "FLO0209",
      "question": "ପର୍ବତଗୁଡ଼ିକ ପାଣିରେ ପଡ଼ିବା ପରେ କ’ଣ ଦୃଶ୍ୟ ହେଉନଥିଲା?",
      "options": {
        "A": "ମାଛ",
        "B": "ବୁଦ୍ବୁଦ (ପାଣି ଫୋଟକା)",
        "C": "ଢେଉ",
        "D": "ଶାମୁକା"
      },
      "answer": "B",
      "explanation": "ପର୍ବତଗୁଡ଼ିକ ଜଳରେ ବୁଡ଼ିଯାଉଥିବାରୁ ସେଠାରେ ବୁଦ୍ବୁଦ ମଧ୍ୟ ଦେଖାଯାଉନଥିଲା।",
      "difficulty": "medium"
    },
    {
      "id": "FLO0210",
      "question": "ରାମଚନ୍ଦ୍ର କେଉଁ ଦେବତାଙ୍କୁ ପ୍ରସନ୍ନ କରିବା ପାଇଁ ଅନଶନ କରିଥିଲେ?",
      "options": {
        "A": "ଅଗ୍ନି",
        "B": "ବରୁଣ",
        "C": "ଇନ୍ଦ୍ର",
        "D": "ପବନ"
      },
      "answer": "B",
      "explanation": "ଜଳାଧିପତି ବରୁଣଙ୍କୁ ପ୍ରସନ୍ନ କରିବା ପାଇଁ ସେ ଅନଶନ କରିଥିଲେ।",
      "difficulty": "easy"
    },
    {
      "id": "FLO0211",
      "question": "ରାମଚନ୍ଦ୍ର କେଉଁ ଶଯ୍ୟାରେ ଶୟନ କରିଥିଲେ?",
      "options": {
        "A": "ପୁଷ୍ପ ଶଯ୍ୟା",
        "B": "ଦର୍ଭ ଶଯ୍ୟା (କୁଶ ଶଯ୍ୟା)",
        "C": "ଭୂମି ଶଯ୍ୟା",
        "D": "ରତ୍ନ ଶଯ୍ୟା"
      },
      "answer": "B",
      "explanation": "ସେ ଅନାହାରରେ କୁଶ ବା ଦର୍ଭ ଶଯ୍ୟାରେ ଶୟନ କରିଥିଲେ।",
      "difficulty": "medium"
    },
    {
      "id": "FLO0212",
      "question": "‘ଦଶଶିର’ ବୋଲି କବିତାରେ କାହାକୁ କୁହାଯାଇଛି?",
      "options": {
        "A": "ବିଭୀଷଣ",
        "B": "କୁମ୍ଭକର୍ଣ୍ଣ",
        "C": "ରାବଣ",
        "D": "ଇନ୍ଦ୍ରଜିତ"
      },
      "answer": "C",
      "explanation": "ରାବଣର ଦଶଟି ମୁଣ୍ଡ ଥିବାରୁ ତାଙ୍କୁ ଦଶଶିର କୁହାଯାଏ।",
      "difficulty": "easy"
    },
    {
      "id": "FLO0213",
      "question": "ରାବଣ କେଉଁ ଦୁଇଜଣ ମନ୍ତ୍ରୀଙ୍କୁ ଦୂତ ଭାବେ ପଠାଇଥିଲେ?",
      "options": {
        "A": "ଶୁକ ଓ ସାରଣ",
        "B": "ମାଲ୍ୟବାନ ଓ ପ୍ରହସ୍ତ",
        "C": "ଅହି ଓ ମହି",
        "D": "ଖର ଓ ଦୂଷଣ"
      },
      "answer": "A",
      "explanation": "ରାବଣ ଶୁକ ଓ ସାରଣଙ୍କୁ ଚାର ବା ଦୂତ ଭାବେ ପଠାଇଥିଲେ।",
      "difficulty": "easy"
    },
    {
      "id": "FLO0214",
      "question": "ରାବଣ ବିଭୀଷଣଙ୍କ ପାଖକୁ କି ବାର୍ତ୍ତା ପଠାଇଥିଲେ?",
      "options": {
        "A": "ଯୁଦ୍ଧ ବନ୍ଦ କରିବାକୁ",
        "B": "ଜ୍ୟେଷ୍ଠ ଭ୍ରାତା ପିତା ସମାନ ବୋଲି କହିବାକୁ",
        "C": "କ୍ଷମା ମାଗିବାକୁ",
        "D": "ରାଜ୍ୟ ଛାଡ଼ିବାକୁ"
      },
      "answer": "B",
      "explanation": "ଜ୍ୟେଷ୍ଠ ଭ୍ରାତା ପିତା ସହିତ ସମାନ, ତେଣୁ ବିଭୀଷଣ ଫେରିଆସିବା ଉଚିତ ବୋଲି କହିଥିଲେ।",
      "difficulty": "medium"
    },
    {
      "id": "FLO0215",
      "question": "ରାବଣ କାହାକୁ ପିତା-ଶତ୍ରୁ ବୋଲି କହିଥିଲେ?",
      "options": {
        "A": "ରାମଙ୍କୁ",
        "B": "ଅଙ୍ଗଦକୁ",
        "C": "ହନୁମାନଙ୍କୁ",
        "D": "ଲକ୍ଷ୍ମଣଙ୍କୁ"
      },
      "answer": "B",
      "explanation": "ଅଙ୍ଗଦର ପିତା ବାଳୀଙ୍କୁ ରାମ ହତ୍ୟା କରିଥିବାରୁ ସେ ପିତା-ଶତ୍ରୁ ବୋଲି କୁହାଯାଇଛି।",
      "difficulty": "medium"
    },
    {
      "id": "FLO0216",
      "question": "ଅଙ୍ଗଦର ବାପାଙ୍କ ନାମ କ’ଣ ଥିଲା?",
      "options": {
        "A": "ସୁଗ୍ରୀବ",
        "B": "ବାଳୀ",
        "C": "ଜାମ୍ବବାନ",
        "D": "ନଳ"
      },
      "answer": "B",
      "explanation": "ଅଙ୍ଗଦ କିସ୍କିନ୍ଧ୍ୟା ରାଜା ବାଳୀଙ୍କ ପୁତ୍ର ଥିଲେ।",
      "difficulty": "easy"
    },
    {
      "id": "FLO0217",
      "question": "‘ବିଭୂତିଭୂଷଣ’ ଶବ୍ଦଟି ଏଠାରେ କାହା ଉଦ୍ଦେଶ୍ୟରେ ବ୍ୟବହୃତ?",
      "options": {
        "A": "ରାବଣ",
        "B": "ରାମଚନ୍ଦ୍ର",
        "C": "ଶିବ",
        "D": "ବିଭୀଷଣ"
      },
      "answer": "B",
      "explanation": "ବନବାସୀ ରୂପେ ଭସ୍ମ ଲେପନ କରିଥିବା ରାମଚନ୍ଦ୍ରଙ୍କୁ ଏଠାରେ ବିଭୂତିଭୂଷଣ କୁହାଯାଇଛି।",
      "difficulty": "hard"
    },
    {
      "id": "FLO0218",
      "question": "ଶୁକ ଓ ସାରଣ କେଉଁ ରୂପରେ ଆକାଶରେ ଉଡ଼ି ଯାଇଥିଲେ?",
      "options": {
        "A": "ମୟୂର",
        "B": "ବର୍ତ୍ତକ (ପକ୍ଷୀ ବିଶେଷ)",
        "C": "ଚିଲ",
        "D": "କାଉ"
      },
      "answer": "B",
      "explanation": "ସେମାନେ ବର୍ତ୍ତକ ବା ଟେଣ୍ଟେଇ ପକ୍ଷୀ ସ୍ବରୂପ ହୋଇ ଉଡ଼ି ଯାଇଥିଲେ।",
      "difficulty": "hard"
    },
    {
      "id": "FLO0219",
      "question": "ରାବଣକୁ କବିତାରେ ‘ବିଂଶତିକର’ କାହିଁକି କୁହାଯାଇଛି?",
      "options": {
        "A": "ତାର ୨୦ଟି ମୁଣ୍ଡ ଥିବାରୁ",
        "B": "ତାର ୨୦ଟି ହାତ ଥିବାରୁ",
        "C": "ସେ ୨୦ ବର୍ଷ ରାଜତ୍ଵ କରିଥିବାରୁ",
        "D": "ସେ ୨୦ଟି ଯୁଦ୍ଧ ଜିତିଥିବାରୁ"
      },
      "answer": "B",
      "explanation": "ବିଂଶତି ଅର୍ଥ କୋଡ଼ିଏ ଏବଂ କର ଅର୍ଥ ହାତ।",
      "difficulty": "medium"
    },
    {
      "id": "FLO0220",
      "question": "ଅଙ୍ଗଦ ଦୂତମାନଙ୍କୁ କିପରି ପ୍ରହାର କରିଥିଲେ?",
      "options": {
        "A": "ଗଦା ପ୍ରହାର",
        "B": "ତଳ (ଚାପୁଡ଼ା) ପ୍ରହାର",
        "C": "ପଥର ମାଡ଼",
        "D": "ବାଣ ପ୍ରହାର"
      },
      "answer": "B",
      "explanation": "ଅଙ୍ଗଦ ଦୂତମାନଙ୍କୁ ଚାପୁଡ଼ା ବା ତଳ ପ୍ରହାର କରିଥିଲେ।",
      "difficulty": "medium"
    },
    {
      "id": "FLO0221",
      "question": "ଅଙ୍ଗଦର ପ୍ରହାର କାହା ସହିତ ସମାନ ଥିଲା?",
      "options": {
        "A": "ପବନ",
        "B": "ବଜ୍ରାଘାତ",
        "C": "ବର୍ଷା",
        "D": "ଭୂମିକମ୍ପ"
      },
      "answer": "B",
      "explanation": "ଅଙ୍ଗଦଙ୍କ ଚାପୁଡ଼ା ବଜ୍ରାଘାତ ସମାନ କଷ୍ଟଦାୟକ ଥିଲା।",
      "difficulty": "medium"
    },
    {
      "id": "FLO0222",
      "question": "ଶୁକ ଓ ସାରଣ କାହାର ପ୍ରସନ୍ନତା ଯୋଗୁଁ ବଞ୍ଚିଗଲେ ବୋଲି କହିଥିଲେ?",
      "options": {
        "A": "ରାବଣ",
        "B": "ବିନ୍ଧ୍ୟ ଭାନୁ (ଅଗସ୍ତି)",
        "C": "ଶ୍ରୀରାମ",
        "D": "ଦଇବ"
      },
      "answer": "B",
      "explanation": "ଅଗସ୍ତି ଋଷିଙ୍କ ପରି କେହି ପରମ ପୁଣ୍ୟାତ୍ମାଙ୍କ ଆଶୀର୍ବାଦ ଯୋଗୁଁ ସେମାନେ ବଞ୍ଚିଗଲେ।",
      "difficulty": "hard"
    },
    {
      "id": "FLO0223",
      "question": "ରାମଙ୍କ ସୈନ୍ୟବାହିନୀରେ କେତେ ‘ଶଙ୍ଖ’ ସୈନ୍ୟ ଥିଲେ?",
      "options": {
        "A": "୧୦୦",
        "B": "ଅଜସ୍ର (ସମୁଦ୍ରରେ ଶଙ୍ଖ ନଥିବା ସଂଖ୍ୟକ)",
        "C": "୧୦",
        "D": "୫"
      },
      "answer": "B",
      "explanation": "ସମୁଦ୍ରରେ ଯେତେ ଶଙ୍ଖ ନାହିଁ, ରାମଙ୍କର ତେତେ ଶଙ୍ଖ (ସଂଖ୍ୟା ବିଶେଷ) ସୈନ୍ୟ ଥିଲେ।",
      "difficulty": "hard"
    },
    {
      "id": "FLO0224",
      "question": "ରାମଙ୍କର କେଉଁ କାର୍ଯ୍ୟକୁ ରାବଣ ହୀନ ପରାକ୍ରମ ବୋଲି କହିଥିଲେ?",
      "options": {
        "A": "ସେତୁ ବାନ୍ଧିବା",
        "B": "କୁଶଶଯ୍ୟାରେ ଶୋଇବା",
        "C": "ବନବାସ ଯିବା",
        "D": "ବିଭୀଷଣକୁ ଆଶ୍ରୟ ଦେବା"
      },
      "answer": "B",
      "explanation": "ସମୁଦ୍ର କୂଳରେ ରାମଚନ୍ଦ୍ର କୁଶଶଯ୍ୟାରେ ଶୋଇବାକୁ ରାବଣ ହୀନ ପରାକ୍ରମ ବୋଲି ଉପହାସ କରିଥିଲା।",
      "difficulty": "medium"
    },
    {
      "id": "FLO0225",
      "question": "‘ଫି ଫି କୃତ’ ଶବ୍ଦର ଅର୍ଥ କ’ଣ?",
      "options": {
        "A": "ହସିବା",
        "B": "ଫିଫିକାର ଶବ୍ଦ (ଜଳରେ ପଡ଼ିବା ଶବ୍ଦ)",
        "C": "ରାଗିବା",
        "D": "ଦୌଡ଼ିବା"
      },
      "answer": "B",
      "explanation": "ଜଳରେ ପର୍ବତ ପଡ଼ିବା ସମୟରେ ହେଉଥିବା ବିଶେଷ ଶବ୍ଦ।",
      "difficulty": "medium"
    },
    {
      "id": "FLO0226",
      "question": "‘ବୁଧେ’ ଶବ୍ଦଟି କାହାକୁ ବୁଝାଏ?",
      "options": {
        "A": "ମୂର୍ଖମାନଙ୍କୁ",
        "B": "ପଣ୍ଡିତମାନଙ୍କୁ",
        "C": "ସୈନିକମାନଙ୍କୁ",
        "D": "ଦାନବମାନଙ୍କୁ"
      },
      "answer": "B",
      "explanation": "ବୁଧେ ଅର୍ଥ ଜ୍ଞାନୀ ବା ପଣ୍ଡିତମାନେ।",
      "difficulty": "medium"
    },
    {
      "id": "FLO0227",
      "question": "‘ପିତୃବ୍ୟ’ ଶବ୍ଦର ଅର୍ଥ କ’ଣ?",
      "options": {
        "A": "ପିତା",
        "B": "ମାମୁ",
        "C": "କକା (ବାପାଙ୍କ ସାନଭାଇ)",
        "D": "ଭାଇ"
      },
      "answer": "C",
      "explanation": "ବାପାଙ୍କ ସାନଭାଇଙ୍କୁ ପିତୃବ୍ୟ କୁହାଯାଏ।",
      "difficulty": "medium"
    },
    {
      "id": "FLO0228",
      "question": "‘ବୈଦେହୀଶ ବିଳାସ’ କାବ୍ୟଟି କେଉଁ ରାଗରେ ଲେଖାଯାଇଛି?",
      "options": {
        "A": "କଳସା",
        "B": "ଆଶାବରୀ",
        "C": "ଚୋଖି",
        "D": "କାମୋଦୀ"
      },
      "answer": "B",
      "explanation": "ପାଠ୍ୟ ଅଂଶଟି ‘ଆଶାବରୀ’ ରାଗରେ ରଚିତ।",
      "difficulty": "medium"
    },
    {
      "id": "FLO0229",
      "question": "କବି ଉପେନ୍ଦ୍ର ଭଞ୍ଜଙ୍କୁ କେଉଁ ଉପାଧି ମିଳିଛି?",
      "options": {
        "A": "ବ୍ୟାସକବି",
        "B": "କବିସମ୍ରାଟ",
        "C": "କବିବର",
        "D": "ସ୍ବଭାବକବି"
      },
      "answer": "B",
      "explanation": "ବଳିଷ୍ଠ କବିତ୍ଵ ପାଇଁ ସେ କବିସମ୍ରାଟ ଭାବେ ପରିଚିତ।",
      "difficulty": "easy"
    },
    {
      "id": "FLO0230",
      "question": "ରାବଣ ଶୁକ-ସାରଣଙ୍କୁ କ’ଣ ରୂପେ ପଠାଇଲେ?",
      "options": {
        "A": "ସେନାପତି",
        "B": "ଚାର (ଦୂତ)",
        "C": "ରାଜପୁତ୍ର",
        "D": "ସାଧୁ"
      },
      "answer": "B",
      "explanation": "ସୂଚନା ସଂଗ୍ରହ ପାଇଁ ସେମାନଙ୍କୁ ଚାର ବା ଦୂତ ଭାବେ ପଠାଇଥିଲେ।",
      "difficulty": "medium"
    },
    {
      "id": "FLO0231",
      "question": "‘ସିନ୍ଧୁ’ ଶବ୍ଦର ପ୍ରତିଶବ୍ଦଟି କ’ଣ?",
      "options": {
        "A": "ନଦୀ",
        "B": "ସମୁଦ୍ର",
        "C": "ଆକାଶ",
        "D": "ଭୂମି"
      },
      "answer": "B",
      "explanation": "ସିନ୍ଧୁ, ସାଗର, ଅର୍ଣ୍ଣବ - ସବୁ ସମୁଦ୍ରର ପ୍ରତିଶବ୍ଦ।",
      "difficulty": "easy"
    },
    {
      "id": "FLO0232",
      "question": "‘ଦେବରିପୁ’ ଶବ୍ଦଟି କାହାକୁ ବୁଝାଏ?",
      "options": {
        "A": "ଦେବତାଙ୍କ ବନ୍ଧୁ",
        "B": "ଦେବତାଙ୍କ ଶତ୍ରୁ (ରାକ୍ଷସ)",
        "C": "ସ୍ଵର୍ଗର ରାଜା",
        "D": "ରାମଚନ୍ଦ୍ର"
      },
      "answer": "B",
      "explanation": "ଦେବତାଙ୍କ ରିପୁ ବା ଶତ୍ରୁ ଅର୍ଥାତ ଦାନବ।",
      "difficulty": "medium"
    },
    {
      "id": "FLO0233",
      "question": "ରାଘବ କାହିଁକି ବିସ୍ମୟରେ ନିଃଶ୍ଵାସ ତେଜିଲେ?",
      "options": {
        "A": "ବରୁଣ ପ୍ରସନ୍ନ ନ ହେବାରୁ",
        "B": "ସୀତାଙ୍କୁ ନ ପାଇବାରୁ",
        "C": "ରାବଣର ସୈନ୍ୟ ଦେଖି",
        "D": "ସେତୁ ଭାଙ୍ଗିଯିବାରୁ"
      },
      "answer": "A",
      "explanation": "ବରୁଣ ପ୍ରସନ୍ନ ନ ହେବାରୁ ରାମ ବିସ୍ମୟରେ ନିଃଶ୍ଵାସ ଛାଡ଼ିଲେ।",
      "difficulty": "hard"
    },
    {
      "id": "FLO0234",
      "question": "‘ପ୍ରାପତି’ ଶବ୍ଦର ଗଦ୍ୟ ରୂପ କ’ଣ?",
      "options": {
        "A": "ପାଇବା",
        "B": "ପ୍ରାପ୍ତି",
        "C": "ପ୍ରସନ୍ନ",
        "D": "ପ୍ରତିକାର"
      },
      "answer": "B",
      "explanation": "କବିତାରେ ବ୍ୟବହୃତ ପ୍ରାପତିର ଗଦ୍ୟ ରୂପ ପ୍ରାପ୍ତି।",
      "difficulty": "medium"
    },
    {
      "id": "FLO0235",
      "question": "‘ଅନୁଜ’ ଶବ୍ଦର ଅର୍ଥ କ’ଣ?",
      "options": {
        "A": "ବଡ଼ଭାଇ",
        "B": "ସାନଭାଇ",
        "C": "ପିତା",
        "D": "ମନ୍ତ୍ରୀ"
      },
      "answer": "B",
      "explanation": "ରାବଣର ଅନୁଜ ବା ସାନଭାଇ ବିଭୀଷଣ।",
      "difficulty": "easy"
    },
    {
      "id": "FLO0236",
      "question": "‘ବୈଦେହୀଶ’ କାହାକୁ କୁହାଯାଏ?",
      "options": {
        "A": "ରାବଣ",
        "B": "ରାମଚନ୍ଦ୍ର",
        "C": "ଜନକ",
        "D": "ଲକ୍ଷ୍ମଣ"
      },
      "answer": "B",
      "explanation": "ବୈଦେହୀ (ସୀତା)ଙ୍କ ଈଶ ବା ସ୍ବାମୀ ହେଉଛନ୍ତି ରାମଚନ୍ଦ୍ର।",
      "difficulty": "medium"
    },
    {
      "id": "FLO0237",
      "question": "ଉପେନ୍ଦ୍ର ଭଞ୍ଜଙ୍କ ରଚିତ ଶବ୍ଦକୋଷର ନାମ କ’ଣ?",
      "options": {
        "A": "ଗୀତାଭିଧାନ",
        "B": "ପୂର୍ଣ୍ଣଚନ୍ଦ୍ର ଭାଷାକୋଷ",
        "C": "ଶବ୍ଦମାଳା",
        "D": "ଅଭିଧାନ ରତ୍ନମାଳା"
      },
      "answer": "A",
      "explanation": "ଗୀତାଭିଧାନ ହେଉଛି ତାଙ୍କର ଏକ ପଦ୍ୟାତ୍ମକ ଶବ୍ଦକୋଷ।",
      "difficulty": "hard"
    },
    {
      "id": "FLO0238",
      "question": "ଶ୍ରୀରାମ କେଉଁ ବଂଶର ଥିଲେ?",
      "options": {
        "A": "ସୂର୍ଯ୍ୟବଂଶ / ରଘୁବଂଶ",
        "B": "ଚନ୍ଦ୍ରବଂଶ",
        "C": "ଯଦୁବଂଶ",
        "D": "ଭଞ୍ଜବଂଶ"
      },
      "answer": "A",
      "explanation": "ରାମଚନ୍ଦ୍ର ସୂର୍ଯ୍ୟବଂଶୀ ବା ରଘୁବଂଶୀ ଥିଲେ।",
      "difficulty": "easy"
    },
    {
      "id": "FLO0239",
      "question": "‘ବାଦ ରଚାଇ’ ଶବ୍ଦର ଅର୍ଥ କ’ଣ?",
      "options": {
        "A": "ଗପ କରି",
        "B": "କଳହ ସୃଷ୍ଟି କରି",
        "C": "ସେତୁ ବାନ୍ଧି",
        "D": "ରାସ୍ତା ତିଆରି କରି"
      },
      "answer": "B",
      "explanation": "ବାଦ ରଚାଇବା ଅର୍ଥାତ ଗଣ୍ଡଗୋଳ ବା କଳହ ସୃଷ୍ଟି କରିବା।",
      "difficulty": "medium"
    },
    {
      "id": "FLO0240",
      "question": "ରାବଣ ଅଙ୍ଗଦକୁ କ’ଣ କରିବାକୁ ପ୍ରବର୍ତ୍ତାଇ ଥିଲେ?",
      "options": {
        "A": "ରାମଙ୍କୁ ହତ୍ୟା କରିବାକୁ",
        "B": "ପିତୃବ୍ୟ (ସୁଗ୍ରୀବ)ଙ୍କ ସହ କଳହ କରି ସୈନ୍ୟ ବାହୁଡ଼ାଇବାକୁ",
        "C": "ଲଙ୍କା ଛାଡ଼ିବାକୁ",
        "D": "ସନ୍ନ୍ୟାସୀ ହେବାକୁ"
      },
      "answer": "B",
      "explanation": "ସୁଗ୍ରୀବଙ୍କ ସହ କଳହ କରାଇ ସୈନ୍ୟଙ୍କୁ ଫେରାଇ ଆଣିବାକୁ କହିଥିଲେ।",
      "difficulty": "hard"
    },
    {
      "id": "FLO0241",
      "question": "‘ଶଙ୍ଖ’ ଶବ୍ଦଟି ଏଠାରେ କେଉଁ ସଂଖ୍ୟାକୁ ବୁଝାଏ?",
      "options": {
        "A": "୧୦୦",
        "B": "ଲକ୍ଷକୋଟି ପରି ଏକ ବିଶାଳ ସଂଖ୍ୟା",
        "C": "ଶୂନ",
        "D": "୧୦୦୦"
      },
      "answer": "B",
      "explanation": "ଏହା ଏକ ବିଶେଷ ଗଣନା ସୂଚକ ଶବ୍ଦ।",
      "difficulty": "hard"
    },
    {
      "id": "FLO0242",
      "question": "‘ଆଶା’ ଶବ୍ଦର ବିପରୀତ ଶବ୍ଦ କ’ଣ?",
      "options": {
        "A": "ଭରସା",
        "B": "ନିରାଶା",
        "C": "ଅଶାନ୍ତି",
        "D": "ପ୍ରତ୍ୟାଶା"
      },
      "answer": "B",
      "explanation": "ଆଶାର ବିପରୀତ ନିରାଶା।",
      "difficulty": "easy"
    },
    {
      "id": "FLO0243",
      "question": "‘ବଜ୍ରାଘାତ’ର ସନ୍ଧି ବିଚ୍ଛେଦ କର।",
      "options": {
        "A": "ବଜ୍ରା + ଘାତ",
        "B": "ବଜ୍ର + ଆଘାତ",
        "C": "ବଜ୍ର + ଘାତ",
        "D": "ବଜ୍ରା + ଆଘାତ"
      },
      "answer": "B",
      "explanation": "ବଜ୍ର + ଆଘାତ = ବଜ୍ରାଘାତ।",
      "difficulty": "medium"
    },
    {
      "id": "FLO0244",
      "question": "‘ପ୍ରତ୍ୟୁତ୍ତର’ର ସନ୍ଧି ବିଚ୍ଛେଦ କର।",
      "options": {
        "A": "ପ୍ରତ୍ୟୁ + ତ୍ତର",
        "B": "ପ୍ରତି + ଉତ୍ତର",
        "C": "ପ୍ରତ୍ୟ + ଉତ୍ତର",
        "D": "ପ୍ରତି + ତର"
      },
      "answer": "B",
      "explanation": "ପ୍ରତି + ଉତ୍ତର = ପ୍ରତ୍ୟୁତ୍ତର",
      "difficulty": "medium"
    },
    {
      "id": "FLO0245",
      "question": "ରାବଣ ଶୁକ ସାରଣଙ୍କୁ ଦେଖି କିପରି ହସିଲା?",
      "options": {
        "A": "ଅଟ୍ଟହାସ୍ୟ",
        "B": "ମନ୍ଦହାସ (ଅଳ୍ପ ହସ)",
        "C": "ଉଚ୍ଚ ହସ",
        "D": "ବ୍ୟଙ୍ଗ ହସ"
      },
      "answer": "B",
      "explanation": "ସେମାନଙ୍କ ଦୁରବସ୍ଥା ଦେଖି ରାବଣ ମନ୍ଦହାସ କରିଥିଲେ।",
      "difficulty": "medium"
    },
    {
      "id": "FLO0246",
      "question": "‘ବିନ୍ଧ୍ୟ ଭାନୁ’ କାହାକୁ କୁହାଯାଏ?",
      "options": {
        "A": "ଅଗସ୍ତି ଋଷି",
        "B": "ରାମଚନ୍ଦ୍ର",
        "C": "ସୂର୍ଯ୍ୟ",
        "D": "ହନୁମାନ"
      },
      "answer": "A",
      "explanation": "ଅଗସ୍ତି ଋଷି ବିନ୍ଧ୍ୟ ପର୍ବତର ଗର୍ବ ଖର୍ବ କରିଥିବାରୁ ତାଙ୍କୁ ବିନ୍ଧ୍ୟ ଭାନୁ କୁହାଯାଏ।",
      "difficulty": "hard"
    },
    {
      "id": "FLO0247",
      "question": "‘ନିଃଶ୍ଵାସ’ର ସନ୍ଧି ବିଚ୍ଛେଦ କର।",
      "options": {
        "A": "ନିଶ + ଶ୍ଵାସ",
        "B": "ନିଃ + ଶ୍ଵାସ",
        "C": "ନି + ଶ୍ଵାସ",
        "D": "ନିର + ଶ୍ଵାସ"
      },
      "answer": "B",
      "explanation": "ନିଃ + ଶ୍ଵାସ = ନିଃଶ୍ଵାସ।",
      "difficulty": "medium"
    },
    {
      "id": "FLO0248",
      "question": "ଶିଳ୍ପୀମାନେ ପର୍ବତ ପକାଇବା ବେଳେ କେଉଁ ଶବ୍ଦ ହେଉଥିଲା?",
      "options": {
        "A": "ଘଡ଼ଘଡ଼ି",
        "B": "ଫି ଫି କୃତ",
        "C": "ଝଣ ଝଣ",
        "D": "ଖଳ ଖଳ"
      },
      "answer": "B",
      "explanation": "ଜଳରେ ବଡ଼ ପଥର ପଡ଼ିବା ବେଳେ ଫିଫିକାର ଶବ୍ଦ ହେଉଥିଲା।",
      "difficulty": "medium"
    },
    {
      "id": "FLO0249",
      "question": "ଉପେନ୍ଦ୍ର ଭଞ୍ଜଙ୍କ କେଉଁ କୃତି ଏକ ‘ଗୀତାତ୍ମକ ଆଳଙ୍କାରିକ’ ରଚନା?",
      "options": {
        "A": "ଲାବଣ୍ୟବତୀ",
        "B": "ରସପଞ୍ଚକ",
        "C": "ବୈଦେହୀଶ ବିଳାସ",
        "D": "ପ୍ରେମ ସୁଧାନିଧି"
      },
      "answer": "B",
      "explanation": "ରସପଞ୍ଚକ ତାଙ୍କର ଏକ ପ୍ରସିଦ୍ଧ ଗୀତାତ୍ମକ ରଚନା।",
      "difficulty": "hard"
    },
    {
      "id": "FLO0250",
      "question": "‘ପ୍ରସନ୍ନ’ ଶବ୍ଦର ବିପରୀତ ଶବ୍ଦ କ’ଣ?",
      "options": {
        "A": "ଖୁସି",
        "B": "ବିଷଣ୍ଣ",
        "C": "ଶାନ୍ତ",
        "D": "ସରଳ"
      },
      "answer": "B",
      "explanation": "ପ୍ରସନ୍ନର ବିପରୀତ ବିଷଣ୍ଣ ବା ଅପ୍ରସନ୍ନ।",
      "difficulty": "medium"
    },
    {
      "id": "FLO0251",
      "question": "ଏହି କବିତାରେ ‘ବରଗିଲା’ ଶବ୍ଦର ଅର୍ଥ କ’ଣ?",
      "options": {
        "A": "ବରଣ କଲା",
        "B": "ପଠାଇଲା",
        "C": "ଧରିଲା",
        "D": "ଗଲା"
      },
      "answer": "B",
      "explanation": "ରାବଣ ଶୁକ ସାରଣଙ୍କୁ ଦୂତ ଭାବେ ବରଗିଲା ବା ପଠାଇଲା।",
      "difficulty": "hard"
    },
    {
      "id": "FLO0252",
      "question": "ରାବଣର କେତୋଟି ହାତ ଥିଲା ବୋଲି ବର୍ଣ୍ଣିତ?",
      "options": {
        "A": "୧୦",
        "B": "୨୦ (ବିଂଶତି)",
        "C": "୪",
        "D": "୧୦୦"
      },
      "answer": "B",
      "explanation": "ରାବଣକୁ ବିଂଶତିକର ବୋଲି କୁହାଯାଇଛି।",
      "difficulty": "easy"
    },
    {
      "id": "FLO0253",
      "question": "‘ହୀନ ପରାକ୍ରମ’ ଶବ୍ଦରେ କେଉଁ ସମାସ ଅଛି?",
      "options": {
        "A": "ଦ୍ଵନ୍ଦ୍ଵ",
        "B": "ବହୁବ୍ରୀହି",
        "C": "କର୍ମଧାରୟ",
        "D": "ତତ୍ପୁରୁଷ"
      },
      "answer": "B",
      "explanation": "ହୀନ ଅଟେ ପରାକ୍ରମ ଯାହାର - ବହୁବ୍ରୀହି।",
      "difficulty": "hard"
    },
    {
      "id": "FLO0254",
      "question": "ରାଘବ କାହିଁକି ‘ବିସ୍ମଇ’ ହେଲେ?",
      "options": {
        "A": "ସମୁଦ୍ର ପୋତି ନ ପାରିବାରୁ",
        "B": "ବରୁଣ ପ୍ରକଟ ନ ହେବାରୁ",
        "C": "ରାବଣର ମାୟା ଦେଖି",
        "D": "ଉପରୋକ୍ତ ସମସ୍ତ"
      },
      "answer": "B",
      "explanation": "ବରୁଣ ଦେବତା ସନ୍ତୁଷ୍ଟ ହୋଇ ଦର୍ଶନ ନ ଦେବାରୁ ସେ ଆଶ୍ଚର୍ଯ୍ୟ ହେଲେ।",
      "difficulty": "medium"
    },
    {
      "id": "FLO0255",
      "question": "ଏହି କବିତାରେ ‘ଦଇବ’ ଶବ୍ଦ କେଉଁ ଅର୍ଥରେ ବ୍ୟବହୃତ?",
      "options": {
        "A": "ଦେବତା",
        "B": "ଭାଗ୍ୟ",
        "C": "ଆକାଶ",
        "D": "ରାକ୍ଷସ"
      },
      "answer": "B",
      "explanation": "ଦଇବ ଅର୍ଥ ଭାଗ୍ୟ ବା ନିୟତି।",
      "difficulty": "medium"
    }
  ]
}